mcal/__init__.py
mcal/mcal.py
mcal/calculations/__init__.py
mcal/calculations/hopping_mobility_model.py
mcal/calculations/rcal.py
mcal/calculations/tcal.py
mcal/constants/element_properties.csv
mcal/utils/__init__.py
mcal/utils/cif_reader.py
mcal/utils/gaus_log_reader.py
mcal/utils/gjf_maker.py
yu_mcal-0.1.1.dist-info/METADATA
yu_mcal-0.1.1.dist-info/WHEEL
yu_mcal-0.1.1.dist-info/entry_points.txt
yu_mcal-0.1.1.dist-info/licenses/LICENSE
yu_mcal-0.1.1.dist-info/RECORD
